aisasconnector/__init__.py
aisasconnector/base.py
aisasconnector/mg_cntr.py
aisasconnector/pg_cntr.py
ai_sas_connector-0.0.4.dist-info/LICENSE.txt
ai_sas_connector-0.0.4.dist-info/METADATA
ai_sas_connector-0.0.4.dist-info/WHEEL
ai_sas_connector-0.0.4.dist-info/top_level.txt
ai_sas_connector-0.0.4.dist-info/RECORD
