Metadata-Version: 2.1
Name: ai-sas-connector
Version: 0.0.4
Summary: ai sas connector
Author: dhsun
Author-email: sunehd564@gmail.com
Classifier: Programming Language :: Python :: 3
Classifier: License :: OSI Approved :: MIT License
Classifier: Operating System :: OS Independent
Requires-Python: >=3.6
License-File: LICENSE.txt
